AUTHORS.rst
CONTRIBUTING.rst
HISTORY.rst
LICENSE
MANIFEST.in
README.rst
setup.cfg
setup.py
dart_search.egg-info/PKG-INFO
dart_search.egg-info/SOURCES.txt
dart_search.egg-info/dependency_links.txt
dart_search.egg-info/not-zip-safe
dart_search.egg-info/top_level.txt
darts/__init__.py
darts/darts.py
test/test_darts.py